{"fields": [{"field_name": "SELLER_STATE", "value_id": [58], "value_text": ["HOSKOTETALUK"], "key_id": [], "key_text": []}, {"field_name": "SELLER_ID", "value_id": [7, 8], "value_text": ["CIN:A10002AA1710AL", "B001995"], "key_id": [], "key_text": []}, {"field_name": "SELLER_NAME", "value_id": [3], "value_text": ["VIRTUALCOMPANYIND"], "key_id": [], "key_text": []}, {"field_name": "SELLER_ADDRESS", "value_id": [9, 10, 11], "value_text": ["VirtualAddr.", "255.0.0.0,", "India"], "key_id": [], "key_text": []}, {"field_name": "SELLER_GSTIN_NUMBER", "value_id": [16], "value_text": ["17ABCDEF123GXYZ"], "key_id": [], "key_text": []}, {"field_name": "COUNTRY_OF_ORIGIN", "value_id": [11], "value_text": ["India"], "key_id": [], "key_text": []}, {"field_name": "DESCRIPTION", "value_id": [28, 29], "value_text": ["TAX", "INVOICE-P01234567"], "key_id": [], "key_text": []}, {"field_name": "INVOICE_NUMBER", "value_id": [34], "value_text": ["1234"], "key_id": [], "key_text": []}, {"field_name": "INVOICE_DATE", "value_id": [35], "value_text": ["/01.07.2017"], "key_id": [], "key_text": []}, {"field_name": "TOTAL_INVOICE_AMOUNT_ENTERED_BY_WH_OPERATOR", "value_id": [198, 199, 200, 201, 202, 203, 204], "value_text": ["Thirteen", "thousand", "eighteen", "and", "Paise", "Sixty-six", "only"], "key_id": [], "key_text": []}, {"field_name": "PO_NUMBER", "value_id": [53], "value_text": ["PO1234567"], "key_id": [], "key_text": []}, {"field_name": "BUYER_GSTIN_NUMBER", "value_id": [54], "value_text": ["GSTIN:07AABBC8888G1AZ1"], "key_id": [], "key_text": []}, {"field_name": "SHIP_TO_ADDRESS", "value_id": [24, 26, 37, 38], "value_text": ["Reciever", "Companylnd", "111000", "India"], "key_id": [], "key_text": []}, {"field_name": "HSN", "value_id": [107, 126, 125], "value_text": ["13019013", "04059020", "04090000"], "key_id": [], "key_text": []}, {"field_name": "TITLE", "value_id": [103, 104, 105, 106, 117, 118, 120, 116, 119], "value_text": ["DUMMY", "PRODUCT", "FOR", "EVALUATION", "DUMMY", "PRODUCT FOR", "EVALUATION", "DUMMY", "PRODUCT FOREVALUATION"], "key_id": [], "key_text": []}, {"field_name": "QUANTITY", "value_id": [135, 137, 136], "value_text": ["120", "50", "12"], "key_id": [], "key_text": []}, {"field_name": "UNIT_PRICE", "value_id": [108, 128, 127], "value_text": ["32.17", "101.73", "196.06"], "key_id": [], "key_text": []}, {"field_name": "DISCOUNT_PERCENT", "value_id": [147, 146, 145], "value_text": ["0.00", "0.00", "0.00"], "key_id": [], "key_text": []}, {"field_name": "SGST_PERCENT", "value_id": [165, 164, 163], "value_text": ["2.50", "6.00", "2.50"], "key_id": [], "key_text": []}, {"field_name": "CGST_PERCENT", "value_id": [157, 156, 155], "value_text": ["2.50", "6.00", "2.50"], "key_id": [], "key_text": []}, {"field_name": "IGST_PERCENT", "value_id": [173, 172, 171], "value_text": ["00", "0.00", "0.00"], "key_id": [], "key_text": []}, {"field_name": "TOTAL_AMOUNT", "value_id": [183, 182, 181], "value_text": ["053.42", "494.88", "2,470.36"], "key_id": [], "key_text": []}, {"field_name": "CURRENCY", "value_id": [], "value_text": [], "key_id": [], "key_text": []}, {"field_name": "DUE_DATE", "value_id": [], "value_text": [], "key_id": [], "key_text": []}, {"field_name": "PRODUCT_ID", "value_id": [], "value_text": [], "key_id": [], "key_text": []}], "global_attributes": {"file_id": "Sample6_0.png"}, "text_boxes": [{"text": "Original", "id": 0, "bbox": [1678, 44, 1761, 64]}, {"text": "for", "id": 1, "bbox": [1765, 44, 1797, 60]}, {"text": "Recipient", "id": 2, "bbox": [1803, 44, 1899, 62]}, {"text": "VIRTUALCOMPANYIND", "id": 3, "bbox": [881, 64, 1351, 105]}, {"text": "Duplicate", "id": 4, "bbox": [1678, 81, 1773, 99]}, {"text": "for", "id": 5, "bbox": [1777, 81, 1809, 97]}, {"text": "Supplier/Transporter", "id": 6, "bbox": [1814, 78, 2030, 103]}, {"text": "CIN:A10002AA1710AL", "id": 7, "bbox": [101, 154, 358, 174]}, {"text": "B001995", "id": 8, "bbox": [360, 154, 460, 174]}, {"text": "VirtualAddr.", "id": 9, "bbox": [920, 121, 1086, 152]}, {"text": "255.0.0.0,", "id": 10, "bbox": [1094, 121, 1238, 154]}, {"text": "India", "id": 11, "bbox": [1248, 123, 1319, 152]}, {"text": "Triplicate", "id": 12, "bbox": [1676, 115, 1777, 137]}, {"text": "for", "id": 13, "bbox": [1779, 117, 1811, 133]}, {"text": "Supplier", "id": 14, "bbox": [1816, 115, 1902, 138]}, {"text": "GSTIN:", "id": 15, "bbox": [99, 182, 180, 204]}, {"text": "17ABCDEF123GXYZ", "id": 16, "bbox": [186, 182, 425, 204]}, {"text": "111000", "id": 17, "bbox": [103, 374, 186, 395]}, {"text": "Buver:", "id": 18, "bbox": [103, 309, 176, 331]}, {"text": "Reciever", "id": 19, "bbox": [105, 346, 202, 364]}, {"text": "Reciever", "id": 20, "bbox": [184, 310, 279, 328]}, {"text": "India", "id": 21, "bbox": [196, 376, 249, 395]}, {"text": "Companylnd", "id": 22, "bbox": [206, 346, 350, 366]}, {"text": "Companylnd", "id": 23, "bbox": [283, 305, 423, 331]}, {"text": "Reciever", "id": 24, "bbox": [762, 346, 859, 364]}, {"text": "Ship-to:Reciever", "id": 25, "bbox": [762, 308, 948, 328]}, {"text": "Companylnd", "id": 26, "bbox": [865, 346, 1011, 366]}, {"text": "Companylnd", "id": 27, "bbox": [952, 308, 1092, 330]}, {"text": "TAX", "id": 28, "bbox": [989, 271, 1041, 293]}, {"text": "INVOICE-P01234567", "id": 29, "bbox": [1041, 271, 1293, 291]}, {"text": "Invoice", "id": 30, "bbox": [1420, 310, 1493, 326]}, {"text": "Gross", "id": 31, "bbox": [1423, 331, 1481, 352]}, {"text": "Weight:", "id": 32, "bbox": [1487, 332, 1564, 350]}, {"text": "No./Date:", "id": 33, "bbox": [1499, 308, 1591, 324]}, {"text": "1234", "id": 34, "bbox": [1678, 306, 1728, 326]}, {"text": "/01.07.2017", "id": 35, "bbox": [1732, 306, 1856, 326]}, {"text": "Page 1 of 1", "id": 36, "bbox": [2036, 267, 2146, 287]}, {"text": "111000", "id": 37, "bbox": [762, 376, 843, 395]}, {"text": "India", "id": 38, "bbox": [853, 376, 905, 395]}, {"text": "Net", "id": 39, "bbox": [1422, 362, 1457, 381]}, {"text": "Weight:", "id": 40, "bbox": [1461, 362, 1538, 383]}, {"text": "Truck", "id": 41, "bbox": [1422, 393, 1479, 411]}, {"text": "No.:", "id": 42, "bbox": [1485, 395, 1526, 411]}, {"text": "Driver", "id": 43, "bbox": [1424, 419, 1483, 438]}, {"text": "No.:", "id": 44, "bbox": [1488, 418, 1527, 440]}, {"text": "Delivery", "id": 45, "bbox": [1424, 444, 1503, 464]}, {"text": "No.:", "id": 46, "bbox": [1507, 445, 1548, 462]}, {"text": "8909289765", "id": 47, "bbox": [1678, 439, 1801, 460]}, {"text": "Order", "id": 48, "bbox": [1424, 470, 1479, 486]}, {"text": "No.:", "id": 49, "bbox": [1485, 470, 1524, 486]}, {"text": "1234567", "id": 50, "bbox": [1680, 466, 1767, 486]}, {"text": "Supplier", "id": 51, "bbox": [1422, 494, 1505, 516]}, {"text": "Ref.:", "id": 52, "bbox": [1511, 494, 1558, 510]}, {"text": "PO1234567", "id": 53, "bbox": [1678, 490, 1795, 512]}, {"text": "GSTIN:07AABBC8888G1AZ1", "id": 54, "bbox": [101, 553, 429, 577]}, {"text": "Place", "id": 55, "bbox": [1425, 517, 1476, 540]}, {"text": "of", "id": 56, "bbox": [1483, 520, 1503, 537]}, {"text": "Supply:", "id": 57, "bbox": [1507, 520, 1584, 539]}, {"text": "HOSKOTETALUK", "id": 58, "bbox": [1678, 516, 1870, 535]}, {"text": "PAN", "id": 59, "bbox": [101, 585, 152, 610]}, {"text": "No.:", "id": 60, "bbox": [154, 587, 200, 610]}, {"text": "ABBCC9098G", "id": 61, "bbox": [204, 585, 362, 610]}, {"text": "GSTIN", "id": 62, "bbox": [760, 553, 835, 577]}, {"text": "07AABBC8888G1AZ1", "id": 63, "bbox": [853, 553, 1094, 577]}, {"text": "State", "id": 64, "bbox": [101, 618, 158, 640]}, {"text": "Code.:", "id": 65, "bbox": [164, 619, 232, 642]}, {"text": "29", "id": 66, "bbox": [239, 620, 265, 638]}, {"text": "PAN", "id": 67, "bbox": [760, 585, 808, 608]}, {"text": "No.:", "id": 68, "bbox": [814, 585, 861, 608]}, {"text": "ABBCC9098G", "id": 69, "bbox": [865, 586, 1023, 608]}, {"text": "State", "id": 70, "bbox": [762, 618, 816, 638]}, {"text": "Code:", "id": 71, "bbox": [822, 620, 887, 638]}, {"text": "29", "id": 72, "bbox": [889, 618, 918, 638]}, {"text": "No", "id": 73, "bbox": [107, 713, 137, 731]}, {"text": "s", "id": 74, "bbox": [115, 683, 131, 699]}, {"text": "Material", "id": 75, "bbox": [229, 683, 310, 699]}, {"text": "Description", "id": 76, "bbox": [316, 683, 427, 701]}, {"text": "HSN/SAC", "id": 77, "bbox": [514, 680, 606, 699]}, {"text": "MRP", "id": 78, "bbox": [626, 680, 670, 697]}, {"text": "Batch", "id": 79, "bbox": [699, 680, 755, 697]}, {"text": "No", "id": 80, "bbox": [760, 679, 788, 700]}, {"text": "Date", "id": 81, "bbox": [816, 711, 861, 729]}, {"text": "Mfg.", "id": 82, "bbox": [816, 680, 859, 701]}, {"text": "Exp.", "id": 83, "bbox": [890, 680, 933, 702]}, {"text": "Date", "id": 84, "bbox": [891, 711, 936, 729]}, {"text": "Qty", "id": 85, "bbox": [956, 680, 991, 699]}, {"text": "CLD", "id": 86, "bbox": [964, 711, 1007, 729]}, {"text": "in", "id": 87, "bbox": [995, 683, 1013, 697]}, {"text": "Qty\u00b7", "id": 88, "bbox": [1026, 677, 1063, 701]}, {"text": "in", "id": 89, "bbox": [1070, 683, 1090, 697]}, {"text": "PCsUOM", "id": 90, "bbox": [1094, 678, 1189, 697]}, {"text": "Rate", "id": 91, "bbox": [1205, 678, 1250, 697]}, {"text": "Dist", "id": 92, "bbox": [1276, 678, 1317, 697]}, {"text": "Taxable", "id": 93, "bbox": [1347, 678, 1424, 697]}, {"text": "CGST", "id": 94, "bbox": [1454, 679, 1512, 696]}, {"text": "CGST", "id": 95, "bbox": [1530, 678, 1586, 695]}, {"text": "Amt", "id": 96, "bbox": [1593, 680, 1633, 697]}, {"text": "SGST", "id": 97, "bbox": [1649, 674, 1708, 697]}, {"text": "SGST/UGST", "id": 98, "bbox": [1718, 676, 1840, 697]}, {"text": "IGST", "id": 99, "bbox": [1850, 676, 1901, 695]}, {"text": "IGST", "id": 100, "bbox": [1927, 676, 1978, 695]}, {"text": "Amt", "id": 101, "bbox": [1984, 678, 2024, 695]}, {"text": "Amount", "id": 102, "bbox": [2077, 676, 2154, 695]}, {"text": "DUMMY", "id": 103, "bbox": [164, 749, 224, 762]}, {"text": "PRODUCT", "id": 104, "bbox": [229, 749, 308, 762]}, {"text": "FOR", "id": 105, "bbox": [312, 749, 346, 764]}, {"text": "EVALUATION", "id": 106, "bbox": [350, 749, 451, 764]}, {"text": "13019013", "id": 107, "bbox": [526, 751, 610, 768]}, {"text": "32.17", "id": 108, "bbox": [632, 751, 681, 768]}, {"text": "%", "id": 109, "bbox": [1284, 711, 1305, 729]}, {"text": "Amount", "id": 110, "bbox": [1349, 711, 1426, 729]}, {"text": "%", "id": 111, "bbox": [1473, 711, 1491, 727]}, {"text": "%", "id": 112, "bbox": [1668, 707, 1688, 727]}, {"text": "Amt", "id": 113, "bbox": [1759, 709, 1799, 727]}, {"text": "%", "id": 114, "bbox": [1868, 709, 1886, 727]}, {"text": "2", "id": 115, "bbox": [129, 788, 141, 800]}, {"text": "DUMMY", "id": 116, "bbox": [164, 822, 227, 837]}, {"text": "DUMMY", "id": 117, "bbox": [164, 786, 224, 800]}, {"text": "PRODUCT FOR", "id": 118, "bbox": [227, 786, 348, 800]}, {"text": "PRODUCT FOREVALUATION", "id": 119, "bbox": [229, 822, 451, 837]}, {"text": "EVALUATION", "id": 120, "bbox": [350, 786, 451, 800]}, {"text": "Page", "id": 121, "bbox": [374, 859, 417, 875]}, {"text": "Sub-Tota", "id": 122, "bbox": [421, 857, 504, 873]}, {"text": "Grand", "id": 123, "bbox": [464, 893, 516, 910]}, {"text": "Total", "id": 124, "bbox": [522, 893, 567, 910]}, {"text": "04090000", "id": 125, "bbox": [526, 822, 610, 839]}, {"text": "04059020", "id": 126, "bbox": [526, 786, 610, 802]}, {"text": "196.06", "id": 127, "bbox": [622, 820, 681, 839]}, {"text": "101.73", "id": 128, "bbox": [622, 786, 681, 802]}, {"text": "3.00", "id": 129, "bbox": [976, 857, 1015, 873]}, {"text": "1.00", "id": 130, "bbox": [978, 820, 1015, 837]}, {"text": "1.00", "id": 131, "bbox": [978, 786, 1015, 802]}, {"text": "1.00", "id": 132, "bbox": [978, 749, 1015, 766]}, {"text": "3.00", "id": 133, "bbox": [1035, 891, 1074, 908]}, {"text": "192", "id": 134, "bbox": [1100, 855, 1132, 873]}, {"text": "120", "id": 135, "bbox": [1102, 749, 1132, 766]}, {"text": "12", "id": 136, "bbox": [1110, 820, 1132, 837]}, {"text": "50", "id": 137, "bbox": [1110, 786, 1132, 802]}, {"text": "192", "id": 138, "bbox": [1159, 891, 1191, 908]}, {"text": "PC", "id": 139, "bbox": [1162, 817, 1189, 838]}, {"text": "PC", "id": 140, "bbox": [1163, 784, 1187, 800]}, {"text": "PC", "id": 141, "bbox": [1163, 749, 1187, 764]}, {"text": "196.06", "id": 142, "bbox": [1199, 818, 1258, 837]}, {"text": "101.73", "id": 143, "bbox": [1201, 784, 1258, 800]}, {"text": "32.17", "id": 144, "bbox": [1209, 749, 1258, 766]}, {"text": "0.00", "id": 145, "bbox": [1280, 820, 1317, 837]}, {"text": "0.00", "id": 146, "bbox": [1280, 786, 1317, 800]}, {"text": "0.00", "id": 147, "bbox": [1280, 749, 1315, 766]}, {"text": "12,012.12", "id": 148, "bbox": [1359, 889, 1443, 908]}, {"text": "12,012.12", "id": 149, "bbox": [1359, 855, 1443, 871]}, {"text": "5,799.00", "id": 150, "bbox": [1368, 784, 1441, 800]}, {"text": "2,352", "id": 151, "bbox": [1370, 818, 1416, 837]}, {"text": "3,860", "id": 152, "bbox": [1370, 749, 1416, 764]}, {"text": "72", "id": 153, "bbox": [1420, 818, 1443, 835]}, {"text": "40", "id": 154, "bbox": [1420, 749, 1441, 764]}, {"text": "2.50", "id": 155, "bbox": [1469, 818, 1507, 835]}, {"text": "6.00", "id": 156, "bbox": [1470, 786, 1508, 799]}, {"text": "2.50", "id": 157, "bbox": [1471, 749, 1507, 764]}, {"text": "503.27", "id": 158, "bbox": [1582, 889, 1641, 908]}, {"text": "503.27", "id": 159, "bbox": [1582, 853, 1639, 869]}, {"text": "347.94", "id": 160, "bbox": [1583, 780, 1639, 801]}, {"text": "58.82", "id": 161, "bbox": [1591, 818, 1639, 835]}, {"text": "96.51", "id": 162, "bbox": [1591, 747, 1637, 764]}, {"text": "2.50", "id": 163, "bbox": [1668, 818, 1704, 835]}, {"text": "6.00", "id": 164, "bbox": [1668, 784, 1704, 800]}, {"text": "2.50", "id": 165, "bbox": [1668, 747, 1704, 764]}, {"text": "503.27", "id": 166, "bbox": [1779, 889, 1836, 905]}, {"text": "503.27", "id": 167, "bbox": [1779, 853, 1836, 869]}, {"text": "347.94", "id": 168, "bbox": [1778, 783, 1836, 798]}, {"text": "58.82", "id": 169, "bbox": [1789, 818, 1838, 835]}, {"text": "96.51", "id": 170, "bbox": [1789, 747, 1834, 764]}, {"text": "0.00", "id": 171, "bbox": [1866, 818, 1903, 835]}, {"text": "0.00", "id": 172, "bbox": [1866, 782, 1903, 798]}, {"text": "00", "id": 173, "bbox": [1878, 747, 1901, 762]}, {"text": "0.00", "id": 174, "bbox": [1996, 853, 2032, 869]}, {"text": "0.00", "id": 175, "bbox": [1998, 887, 2034, 903]}, {"text": "0.00", "id": 176, "bbox": [1996, 782, 2032, 798]}, {"text": "0.00", "id": 177, "bbox": [1998, 816, 2032, 835]}, {"text": "0.00", "id": 178, "bbox": [1996, 747, 2032, 764]}, {"text": "13,018.66", "id": 179, "bbox": [2097, 887, 2180, 903]}, {"text": "13,018.66", "id": 180, "bbox": [2097, 851, 2180, 867]}, {"text": "2,470.36", "id": 181, "bbox": [2107, 816, 2180, 833]}, {"text": "494.88", "id": 182, "bbox": [2122, 782, 2178, 796]}, {"text": "053.42", "id": 183, "bbox": [2122, 745, 2180, 762]}, {"text": "GST", "id": 184, "bbox": [103, 1254, 141, 1270]}, {"text": "Amount", "id": 185, "bbox": [145, 1254, 216, 1270]}, {"text": "Rupees", "id": 186, "bbox": [229, 1254, 295, 1270]}, {"text": "One", "id": 187, "bbox": [300, 1253, 332, 1270]}, {"text": "thousand", "id": 188, "bbox": [338, 1254, 415, 1270]}, {"text": "SIX", "id": 189, "bbox": [419, 1256, 439, 1266]}, {"text": "andPaise", "id": 190, "bbox": [445, 1252, 528, 1270]}, {"text": "Fifty-four", "id": 191, "bbox": [533, 1252, 607, 1273]}, {"text": "only", "id": 192, "bbox": [610, 1254, 644, 1270]}, {"text": "Gross", "id": 193, "bbox": [103, 1284, 156, 1301]}, {"text": "Amount", "id": 194, "bbox": [162, 1287, 231, 1301]}, {"text": "(In", "id": 195, "bbox": [233, 1287, 255, 1301]}, {"text": "Words):", "id": 196, "bbox": [261, 1284, 330, 1303]}, {"text": "Rupees", "id": 197, "bbox": [334, 1284, 399, 1303]}, {"text": "Thirteen", "id": 198, "bbox": [409, 1284, 476, 1302]}, {"text": "thousand", "id": 199, "bbox": [480, 1287, 557, 1301]}, {"text": "eighteen", "id": 200, "bbox": [561, 1284, 632, 1301]}, {"text": "and", "id": 201, "bbox": [636, 1287, 666, 1299]}, {"text": "Paise", "id": 202, "bbox": [670, 1284, 719, 1299]}, {"text": "Sixty-six", "id": 203, "bbox": [723, 1283, 790, 1303]}, {"text": "only", "id": 204, "bbox": [794, 1287, 828, 1301]}, {"text": "Declaration", "id": 205, "bbox": [105, 1398, 231, 1418]}, {"text": "We", "id": 206, "bbox": [241, 1402, 269, 1418]}, {"text": "declare", "id": 207, "bbox": [273, 1404, 334, 1418]}, {"text": "that", "id": 208, "bbox": [338, 1401, 370, 1420]}, {"text": "this", "id": 209, "bbox": [372, 1404, 403, 1418]}, {"text": "INVOICE", "id": 210, "bbox": [405, 1404, 464, 1418]}, {"text": "snows", "id": 211, "bbox": [468, 1404, 520, 1418]}, {"text": "the", "id": 212, "bbox": [524, 1404, 551, 1418]}, {"text": "acta", "id": 213, "bbox": [555, 1404, 606, 1418]}, {"text": "price", "id": 214, "bbox": [608, 1404, 648, 1418]}, {"text": "ot the", "id": 215, "bbox": [652, 1402, 699, 1416]}, {"text": "goods", "id": 216, "bbox": [702, 1404, 754, 1416]}, {"text": "described", "id": 217, "bbox": [755, 1402, 835, 1416]}, {"text": "and", "id": 218, "bbox": [841, 1402, 871, 1416]}, {"text": "that all partculars", "id": 219, "bbox": [877, 1402, 1015, 1414]}, {"text": "are", "id": 220, "bbox": [1020, 1404, 1046, 1412]}, {"text": "true and", "id": 221, "bbox": [1051, 1402, 1118, 1414]}, {"text": "correct.", "id": 222, "bbox": [1124, 1402, 1179, 1416]}, {"text": "This", "id": 223, "bbox": [859, 1476, 895, 1494]}, {"text": "IS", "id": 224, "bbox": [897, 1479, 912, 1491]}, {"text": "Computer", "id": 225, "bbox": [932, 1477, 1013, 1497]}, {"text": "generated", "id": 226, "bbox": [1017, 1479, 1100, 1491]}, {"text": "Invoice", "id": 227, "bbox": [1104, 1477, 1163, 1491]}, {"text": "Subject to", "id": 228, "bbox": [1175, 1475, 1258, 1491]}, {"text": "HaridwarJunsdiction", "id": 229, "bbox": [1262, 1477, 1430, 1491]}]}